<?xml version="1.0" encoding="UTF-8"?>
<timeline clock="90" videoEnabled="f">
  <home color="BA1847"><![CDATA[Brechin City]]></home>
  <away color="000099"><![CDATA[Forfar Athletic]]></away>
  <period>2</period>
  <gameStatus>FINAL</gameStatus>
  <gameStatusText>FT</gameStatusText>
  <events>
    <event id="19628154" clock="7" side="away" type="goal" addedTime="" videoId="">
      <result><![CDATA[<b>Martyn Fotheringham</b> - 7'<br>Goal]]></result>
    </event>
    <event id="19628177" clock="17" side="away" type="goal" addedTime="" videoId="">
      <result><![CDATA[<b>Chris Templeman</b> - 17'<br>Goal]]></result>
    </event>
    <event id="19628219" clock="31" side="away" type="goal" addedTime="" videoId="">
      <result><![CDATA[<b>Darren Dods</b> - 31'<br>Goal]]></result>
    </event>
    <event id="19628229" clock="35" side="away" type="goal" addedTime="" videoId="">
      <result><![CDATA[<b>Dale Hilson</b> - 35'<br>Goal]]></result>
    </event>
    <event id="19628248" clock="42" side="away" type="substitution" addedTime="" videoId="">
      <result><![CDATA[<b>On: Omar Kader</b> - 42'<br>Off: Mark  Baxter]]></result>
    </event>
    <event id="19628272" clock="46" side="home" type="substitution" addedTime="" videoId="">
      <result><![CDATA[<b>On: Paul McLean</b> - 46'<br>Off: Derek Carcary]]></result>
    </event>
    <event id="19628283" clock="51" side="home" type="yellowCard" addedTime="" videoId="">
      <result><![CDATA[<b>Steven Jackson</b> - 51'<br>Yellow Card]]></result>
    </event>
    <event id="19628304" clock="54" side="home" type="yellowCard" addedTime="" videoId="">
      <result><![CDATA[<b>Ewan Moyes</b> - 54'<br>Yellow Card]]></result>
    </event>
    <event id="19628331" clock="61" side="away" type="yellowCard" addedTime="" videoId="">
      <result><![CDATA[<b>Gary Fusco</b> - 61'<br>Yellow Card]]></result>
    </event>
    <event id="19628358" clock="71" side="away" type="substitution" addedTime="" videoId="">
      <result><![CDATA[<b>On: Ross Campbell</b> - 71'<br>Off: James Dale]]></result>
    </event>
    <event id="19628370" clock="75" side="home" type="goal" addedTime="" videoId="">
      <result><![CDATA[<b>Bobby Barr</b> - 75'<br>Goal]]></result>
    </event>
    <event id="19628391" clock="81" side="away" type="goal" addedTime="" videoId="">
      <result><![CDATA[<b>Chris Templeman</b> - 81'<br>Goal]]></result>
    </event>
  </events>
</timeline>
