<?xml version="1.0" encoding="UTF-8"?>
<timeline clock="90" videoEnabled="f">
  <home color="00245D"><![CDATA[LA Galaxy]]></home>
  <away color="91022D"><![CDATA[Colorado Rapids]]></away>
  <period>2</period>
  <gameStatus>FINAL</gameStatus>
  <gameStatusText>FT</gameStatusText>
  <events>
    <event id="7666141" clock="16" side="home" type="yellowCard" addedTime="" videoId="">
      <result><![CDATA[<b>Kevin Harmse</b> - 16'<br>Yellow Card]]></result>
    </event>
    <event id="7666149" clock="40" side="away" type="yellowCard" addedTime="" videoId="">
      <result><![CDATA[<b>Jovan Kirovski</b> - 40'<br>Yellow Card]]></result>
    </event>
    <event id="7666158" clock="46" side="home" type="goal" addedTime="" videoId="">
      <result><![CDATA[<b>Alan Gordon</b> - 46'<br>Goal]]></result>
    </event>
    <event id="7666163" clock="57" side="home" type="substitution" addedTime="" videoId="">
      <result><![CDATA[<b>On: Gavin Glinton</b> - 57'<br>Off: Alan Gordon]]></result>
    </event>
    <event id="7666164" clock="58" side="away" type="substitution" addedTime="" videoId="">
      <result><![CDATA[<b>On: Zach Thornton</b> - 58'<br>Off: Bouna Coundoul]]></result>
    </event>
    <event id="7666169" clock="63" side="home" type="goal" addedTime="" videoId="">
      <result><![CDATA[<b>Edson Buddle</b> - 63'<br>Goal]]></result>
    </event>
    <event id="7666170" clock="64" side="home" type="substitution" addedTime="" videoId="">
      <result><![CDATA[<b>On: Carlos Pavon</b> - 64'<br>Off: Edson Buddle]]></result>
    </event>
    <event id="7666174" clock="66" side="away" type="yellowCard" addedTime="" videoId="">
      <result><![CDATA[<b>Ugo Ihemelu</b> - 66'<br>Yellow Card]]></result>
    </event>
    <event id="7666177" clock="70" side="home" type="goal" addedTime="" videoId="">
      <result><![CDATA[<b>Kyle Martino</b> - 70'<br>Goal]]></result>
    </event>
    <event id="7666178" clock="71" side="away" type="substitution" addedTime="" videoId="">
      <result><![CDATA[<b>On: Jacob Peterson</b> - 71'<br>Off: Facundo Erpen]]></result>
    </event>
    <event id="7666184" clock="80" side="home" type="substitution" addedTime="" videoId="">
      <result><![CDATA[<b>On: Kyle Veris</b> - 80'<br>Off: Ty Harden]]></result>
    </event>
    <event id="7666185" clock="81" side="home" type="yellowCard" addedTime="" videoId="">
      <result><![CDATA[<b>Kyle Veris</b> - 81'<br>Yellow Card]]></result>
    </event>
    <event id="7666187" clock="86" side="away" type="substitution" addedTime="" videoId="">
      <result><![CDATA[<b>On: Omar Cummings</b> - 86'<br>Off: Herculez Gomez]]></result>
    </event>
    <event id="7666189" clock="89" side="away" type="goal" addedTime="" videoId="">
      <result><![CDATA[<b>Mehdi Ballouchy</b> - 89'<br>Goal]]></result>
    </event>
  </events>
</timeline>
