<?xml version="1.0" encoding="UTF-8"?>
<game>
	<options videoEnabled="f">
		<option id="shots">
			<label>Shots</label>
				<subNav>
					<total>Total</total>
					<firstHalf>1st Half</firstHalf>
					<secondHalf>2nd Half</secondHalf>
					<extra>Extra</extra>
					<penalty>Penalties</penalty>
				</subNav>
		</option>
		<option id="goals">
			<label>Goals</label>
			<subNav> </subNav>
		</option>
		<option id="tactical">
			<label>Tactical Formation</label>
			<subNav>
				<label>Select Tactical Formation</label>
				<startFormation>Starting Formation</startFormation>
				<avgFormation>Average Position</avgFormation>
			</subNav>
		</option>
		<option id="heatMap">
			<label>Heat Map</label>
			<subNav>
				<label>Select Heat Map</label>
			</subNav>
		</option>
	</options>
	<icons>
		<icon id="shot">Shot</icon>
		<icon id="goal">Goal</icon>
		<icon id="video">Video Highlight</icon>
	</icons>


	<teams><home id="114" color="0093EC">Napoli</home><away id="111" color="181A21">Juventus</away></teams><attack><entry key="t114" jersey="" avgX="0" avgY="0" posX="0" posY="0" left="0" middle="0" right="0" playerId="-1" teamId="114" position=""><![CDATA[Complete Team]]></entry><entry key="t111" jersey="" avgX="0" avgY="0" posX="0" posY="0" left="0" middle="0" right="0" playerId="-1" teamId="111" position=""><![CDATA[Complete Team]]></entry><entry key="p24836" jersey="3" avgX="0" avgY="0" posX="0" posY="0" left="0" middle="0" right="0" playerId="24836" teamId="111" position="D"><![CDATA[Giorgio Chiellini]]></entry><entry key="p89246" jersey="null" avgX="0" avgY="0" posX="0" posY="0" left="0" middle="0" right="0" playerId="89246" teamId="114" position=""><![CDATA[Cristian Bucchi]]></entry><entry key="p38111" jersey="null" avgX="0" avgY="0" posX="0" posY="0" left="0" middle="0" right="0" playerId="38111" teamId="114" position="F"><![CDATA[Emanuele Calaio]]></entry><entry key="p12952" jersey="10" avgX="0" avgY="0" posX="0" posY="0" left="0" middle="0" right="0" playerId="12952" teamId="111" position="F"><![CDATA[Alessandro Del Piero]]></entry><entry key="p104405" jersey="null" avgX="0" avgY="0" posX="0" posY="0" left="0" middle="0" right="0" playerId="104405" teamId="114" position="D"><![CDATA[Paolo Cannavaro]]></entry></attack><shots><play id="6370972" clock="27" addedTime="" period="1" startX="0.0" startY="1.0" teamId="111" goal="t" ownGoal="f" shootout="f" videoId=""><player><![CDATA[Giorgio Chiellini]]></player><result><![CDATA[<b>Giorgio Chiellini</b> - 27' <br>Goal]]></result><part pId="24836" jersey="3" startX="0.0" startY="1.0"><player><![CDATA[Giorgio Chiellini]]></player><result><![CDATA[<b>Giorgio Chiellini</b><br>Goal]]></result><resultText><![CDATA[Goal]]></resultText></part><topScoreText>(27')</topScoreText><shotByText>Shot by Giorgio Chiellini</shotByText></play><play id="6370973" clock="39" addedTime="" period="1" startX="1.0" startY="0.0" teamId="114" goal="t" ownGoal="f" shootout="f" videoId=""><player><![CDATA[Cristian Bucchi]]></player><result><![CDATA[<b>Cristian Bucchi</b> - 39' <br>Goal]]></result><part pId="89246" jersey="" startX="1.0" startY="0.0"><player><![CDATA[Cristian Bucchi]]></player><result><![CDATA[<b>Cristian Bucchi</b><br>Goal]]></result><resultText><![CDATA[Goal]]></resultText></part><topScoreText>(39')</topScoreText><shotByText>Shot by Cristian Bucchi</shotByText></play><play id="6370974" clock="54" addedTime="" period="2" startX="1.0" startY="0.0" teamId="114" goal="t" ownGoal="f" shootout="f" videoId=""><player><![CDATA[Emanuele Calaio]]></player><result><![CDATA[<b>Emanuele Calaio</b> - 54' <br>Goal]]></result><part pId="38111" jersey="" startX="1.0" startY="0.0"><player><![CDATA[Emanuele Calaio]]></player><result><![CDATA[<b>Emanuele Calaio</b><br>Goal]]></result><resultText><![CDATA[Goal]]></resultText></part><topScoreText>(54')</topScoreText><shotByText>Shot by Emanuele Calaio</shotByText></play><play id="6370975" clock="78" addedTime="" period="2" startX="0.0" startY="1.0" teamId="111" goal="t" ownGoal="f" shootout="f" videoId=""><player><![CDATA[Alessandro Del Piero]]></player><result><![CDATA[<b>Alessandro Del Piero</b> - 78' <br>Goal]]></result><part pId="12952" jersey="10" startX="0.0" startY="1.0"><player><![CDATA[Alessandro Del Piero]]></player><result><![CDATA[<b>Alessandro Del Piero</b><br>Goal]]></result><resultText><![CDATA[Goal]]></resultText></part><topScoreText>(78')</topScoreText><shotByText>Shot by Alessandro Del Piero</shotByText></play><play id="6370976" clock="115" addedTime="" period="4" startX="0.0" startY="1.0" teamId="111" goal="t" ownGoal="f" shootout="f" videoId=""><player><![CDATA[Alessandro Del Piero]]></player><result><![CDATA[<b>Alessandro Del Piero</b> - 115' <br>Goal]]></result><part pId="12952" jersey="10" startX="0.0" startY="1.0"><player><![CDATA[Alessandro Del Piero]]></player><result><![CDATA[<b>Alessandro Del Piero</b><br>Goal]]></result><resultText><![CDATA[Goal]]></resultText></part><topScoreText>(115')</topScoreText><shotByText>Shot by Alessandro Del Piero</shotByText></play><play id="6370977" clock="116" addedTime="" period="4" startX="1.0" startY="0.0" teamId="114" goal="t" ownGoal="f" shootout="f" videoId=""><player><![CDATA[Paolo Cannavaro]]></player><result><![CDATA[<b>Paolo Cannavaro</b> - 116' <br>Goal]]></result><part pId="104405" jersey="" startX="1.0" startY="0.0"><player><![CDATA[Paolo Cannavaro]]></player><result><![CDATA[<b>Paolo Cannavaro</b><br>Goal]]></result><resultText><![CDATA[Goal]]></resultText></part><topScoreText>(116')</topScoreText><shotByText>Shot by Paolo Cannavaro</shotByText></play></shots><gameInfo><homeScore>3</homeScore><awayScore>3</awayScore><clock>116</clock><period>2</period><gameStatus>FINAL</gameStatus><gameStatusText>FT</gameStatusText><addedTime/><pregameWhen>Game Starts at 19:00 +00:00</pregameWhen><pregameWhere/><radioUrl/><videoUrl funct=""/></gameInfo></game>
