<?xml version="1.0" encoding="UTF-8"?>
<game>
	<options videoEnabled="f">
		<option id="shots">
			<label>Shots</label>
				<subNav>
					<total>Total</total>
					<firstHalf>1st Half</firstHalf>
					<secondHalf>2nd Half</secondHalf>
					<extra>Extra</extra>
					<penalty>Penalties</penalty>
				</subNav>
		</option>
		<option id="goals">
			<label>Goals</label>
			<subNav> </subNav>
		</option>
		<option id="tactical">
			<label>Tactical Formation</label>
			<subNav>
				<label>Select Tactical Formation</label>
				<startFormation>Starting Formation</startFormation>
				<avgFormation>Average Position</avgFormation>
			</subNav>
		</option>
		<option id="heatMap">
			<label>Heat Map</label>
			<subNav>
				<label>Select Heat Map</label>
			</subNav>
		</option>
	</options>
	<icons>
		<icon id="shot">Shot</icon>
		<icon id="goal">Goal</icon>
		<icon id="video">Video Highlight</icon>
	</icons>


	<teams><home id="6994" color="005da3">Grenoble</home><away id="3236" color="1a1a1a">Le Havre AC</away></teams><attack><entry key="t6994" jersey="" avgX="0" avgY="0" posX="0" posY="0" left="0" middle="0" right="0" playerId="-1" teamId="6994" position=""><![CDATA[Complete Team]]></entry><entry key="t3236" jersey="" avgX="0" avgY="0" posX="0" posY="0" left="0" middle="0" right="0" playerId="-1" teamId="3236" position=""><![CDATA[Complete Team]]></entry><entry key="p84624" jersey="17" avgX="0" avgY="0" posX="0" posY="0" left="0" middle="0" right="0" playerId="84624" teamId="3236" position=""><![CDATA[Alexandre Bonnet]]></entry><entry key="p106076" jersey="7" avgX="0" avgY="0" posX="0" posY="0" left="0" middle="0" right="0" playerId="106076" teamId="3236" position="M"><![CDATA[Jean-Pascal Fontaine]]></entry><entry key="p131742" jersey="1" avgX="0" avgY="0" posX="0" posY="0" left="0" middle="0" right="0" playerId="131742" teamId="3236" position="G"><![CDATA[Mathieu Gorgelin]]></entry><entry key="p169823" jersey="18" avgX="0" avgY="0" posX="0" posY="0" left="0" middle="0" right="0" playerId="169823" teamId="3236" position=""><![CDATA[Amos Youga]]></entry><entry key="p185523" jersey="22" avgX="0" avgY="0" posX="0" posY="0" left="0" middle="0" right="0" playerId="185523" teamId="3236" position="M"><![CDATA[Victor Lekhal]]></entry><entry key="p194126" jersey="4" avgX="0" avgY="0" posX="0" posY="0" left="0" middle="0" right="0" playerId="194126" teamId="3236" position="D"><![CDATA[Ertugrul Ersoy]]></entry><entry key="p197351" jersey="14" avgX="0" avgY="0" posX="0" posY="0" left="0" middle="0" right="0" playerId="197351" teamId="3236" position="F"><![CDATA[Jamal Thiare]]></entry><entry key="p221355" jersey="25" avgX="0" avgY="0" posX="0" posY="0" left="0" middle="0" right="0" playerId="221355" teamId="3236" position="M"><![CDATA[Barnabas Bese]]></entry><entry key="p245855" jersey="10" avgX="0" avgY="0" posX="0" posY="0" left="0" middle="0" right="0" playerId="245855" teamId="3236" position=""><![CDATA[Alan Dzabana]]></entry><entry key="p245914" jersey="5" avgX="0" avgY="0" posX="0" posY="0" left="0" middle="0" right="0" playerId="245914" teamId="3236" position="D"><![CDATA[Fernand Mayembo]]></entry><entry key="p252186" jersey="6" avgX="0" avgY="0" posX="0" posY="0" left="0" middle="0" right="0" playerId="252186" teamId="3236" position=""><![CDATA[Romain Basque]]></entry><entry key="p255889" jersey="24" avgX="0" avgY="0" posX="0" posY="0" left="0" middle="0" right="0" playerId="255889" teamId="3236" position="M"><![CDATA[Pape Alassane Gueye]]></entry><entry key="p261595" jersey="30" avgX="0" avgY="0" posX="0" posY="0" left="0" middle="0" right="0" playerId="261595" teamId="3236" position=""><![CDATA[Yahia Fofana]]></entry><entry key="p265100" jersey="12" avgX="0" avgY="0" posX="0" posY="0" left="0" middle="0" right="0" playerId="265100" teamId="3236" position=""><![CDATA[Aymen Ben Mohamed]]></entry><entry key="p272195" jersey="3" avgX="0" avgY="0" posX="0" posY="0" left="0" middle="0" right="0" playerId="272195" teamId="3236" position="M"><![CDATA[Umut Meras]]></entry><entry key="p277525" jersey="8" avgX="0" avgY="0" posX="0" posY="0" left="0" middle="0" right="0" playerId="277525" teamId="3236" position="F"><![CDATA[Himad Abdelli]]></entry><entry key="p287645" jersey="23" avgX="0" avgY="0" posX="0" posY="0" left="0" middle="0" right="0" playerId="287645" teamId="3236" position=""><![CDATA[Eric Junior Dina Ebimbe]]></entry><entry key="p300410" jersey="28" avgX="0" avgY="0" posX="0" posY="0" left="0" middle="0" right="0" playerId="300410" teamId="3236" position="D"><![CDATA[Loic Bade]]></entry><entry key="p112549" jersey="14" avgX="0" avgY="0" posX="0" posY="0" left="0" middle="0" right="0" playerId="112549" teamId="6994" position=""><![CDATA[Loic Nestor]]></entry><entry key="p120496" jersey="1" avgX="0" avgY="0" posX="0" posY="0" left="0" middle="0" right="0" playerId="120496" teamId="6994" position="G"><![CDATA[Brice Maubleu]]></entry><entry key="p138409" jersey="8" avgX="0" avgY="0" posX="0" posY="0" left="0" middle="0" right="0" playerId="138409" teamId="6994" position=""><![CDATA[Jonathan Tinhan]]></entry><entry key="p146799" jersey="29" avgX="0" avgY="0" posX="0" posY="0" left="0" middle="0" right="0" playerId="146799" teamId="6994" position="D"><![CDATA[Pierre Gibaud]]></entry><entry key="p164186" jersey="16" avgX="0" avgY="0" posX="0" posY="0" left="0" middle="0" right="0" playerId="164186" teamId="6994" position=""><![CDATA[Papa Demba Camara]]></entry><entry key="p173557" jersey="4" avgX="0" avgY="0" posX="0" posY="0" left="0" middle="0" right="0" playerId="173557" teamId="6994" position="D"><![CDATA[Eric Vandenabeele]]></entry><entry key="p176231" jersey="18" avgX="0" avgY="0" posX="0" posY="0" left="0" middle="0" right="0" playerId="176231" teamId="6994" position="M"><![CDATA[Anthony Belmonte]]></entry><entry key="p181582" jersey="5" avgX="0" avgY="0" posX="0" posY="0" left="0" middle="0" right="0" playerId="181582" teamId="6994" position="D"><![CDATA[Adrien Monfray]]></entry><entry key="p181714" jersey="23" avgX="0" avgY="0" posX="0" posY="0" left="0" middle="0" right="0" playerId="181714" teamId="6994" position="D"><![CDATA[Jerome Mombris]]></entry><entry key="p191328" jersey="17" avgX="0" avgY="0" posX="0" posY="0" left="0" middle="0" right="0" playerId="191328" teamId="6994" position=""><![CDATA[Terell Ondaan]]></entry><entry key="p207002" jersey="21" avgX="0" avgY="0" posX="0" posY="0" left="0" middle="0" right="0" playerId="207002" teamId="6994" position="M"><![CDATA[Jessy Benet]]></entry><entry key="p215132" jersey="24" avgX="0" avgY="0" posX="0" posY="0" left="0" middle="0" right="0" playerId="215132" teamId="6994" position=""><![CDATA[Ibrahima Coulibaly]]></entry><entry key="p235875" jersey="6" avgX="0" avgY="0" posX="0" posY="0" left="0" middle="0" right="0" playerId="235875" teamId="6994" position="M"><![CDATA[Charles Pickel]]></entry><entry key="p251550" jersey="25" avgX="0" avgY="0" posX="0" posY="0" left="0" middle="0" right="0" playerId="251550" teamId="6994" position=""><![CDATA[Abdel Hakim Abdallah]]></entry><entry key="p269291" jersey="22" avgX="0" avgY="0" posX="0" posY="0" left="0" middle="0" right="0" playerId="269291" teamId="6994" position="M"><![CDATA[Arsene Elogo]]></entry><entry key="p270593" jersey="9" avgX="0" avgY="0" posX="0" posY="0" left="0" middle="0" right="0" playerId="270593" teamId="6994" position=""><![CDATA[Krist&#243;fer Ingi Kristinsson]]></entry><entry key="p271675" jersey="7" avgX="0" avgY="0" posX="0" posY="0" left="0" middle="0" right="0" playerId="271675" teamId="6994" position="M"><![CDATA[Willy Johnson]]></entry><entry key="p275008" jersey="2" avgX="0" avgY="0" posX="0" posY="0" left="0" middle="0" right="0" playerId="275008" teamId="6994" position="F"><![CDATA[Moussa Djitte]]></entry></attack><shots><play id="33545042" clock="53" addedTime="" period="2" startX="0.0" startY="1.0" teamId="3236" goal="t" ownGoal="f" shootout="f" videoId=""><player><![CDATA[Jamal Thiare]]></player><result><![CDATA[<b>Jamal Thiare</b> - 53' <br>Goal]]></result><part pId="197351" jersey="14" startX="0.0" startY="1.0"><player><![CDATA[Jamal Thiare]]></player><result><![CDATA[<b>Jamal Thiare</b><br>Goal]]></result><resultText><![CDATA[Goal]]></resultText></part><topScoreText>(53')</topScoreText><shotByText>Shot by Jamal Thiare</shotByText></play><play id="33545319" clock="86" addedTime="" period="2" startX="1.0" startY="0.0" teamId="6994" goal="t" ownGoal="f" shootout="f" videoId=""><player><![CDATA[Jessy Benet]]></player><result><![CDATA[<b>Jessy Benet</b> - 86' <br>Penalty - Scored]]></result><part pId="207002" jersey="21" startX="1.0" startY="0.0"><player><![CDATA[Jessy Benet]]></player><result><![CDATA[<b>Jessy Benet</b><br>Penalty - Scored]]></result><resultText><![CDATA[Penalty - Scored]]></resultText></part><topScoreText>(86' PEN)</topScoreText><shotByText>Shot by Jessy Benet</shotByText></play></shots><gameInfo><homeScore>1</homeScore><awayScore>1</awayScore><clock>90</clock><period>2</period><gameStatus>FINAL</gameStatus><gameStatusText>FT</gameStatusText><addedTime/><pregameWhen>Game Starts at 11:45 GMT</pregameWhen><pregameWhere/><radioUrl/><videoUrl funct=""/></gameInfo></game>
